kdsearch/__init__.py
kdsearch/kdtree.py
kdsearch/statistics.py
kdsearch-1.1.dist-info/DESCRIPTION.rst
kdsearch-1.1.dist-info/METADATA
kdsearch-1.1.dist-info/RECORD
kdsearch-1.1.dist-info/WHEEL
kdsearch-1.1.dist-info/metadata.json
kdsearch-1.1.dist-info/top_level.txt
