Metadata-Version: 2.0
Name: kdsearch
Version: 1.1
Summary: Efficient K-dimensional queries in python using KDTrees with pandas and numpy.
Home-page: https://github.com/lovasoa/kdsearch
Author: Ophir LOJKINE
Author-email: pere.jobs@gmail.com
License: UNKNOWN
Download-URL: https://github.com/lovasoa/kdsearch/archive/1.1.tar.gz
Keywords: tree,search,query,bounding box,index,k-dimensional,dimesnions,data structure
Platform: UNKNOWN
Classifier: Development Status :: 5 - Production/Stable
Classifier: Environment :: Console
Classifier: Operating System :: OS Independent
Classifier: Intended Audience :: Science/Research
Classifier: Programming Language :: Python
Classifier: Programming Language :: Python :: 3.5
Classifier: Programming Language :: Python :: 3.6
Classifier: Topic :: Scientific/Engineering
